{
  "Name": "Super Juice", //The name you would like your object to have, this should be identical to the subfolder name.
  "Description": "The perfect fusion of male and female juices", //Description of the product.
  "Category": "Cooking", //This should match the crop.json Type or for fruit trees should be one of the following: Flower, Fruit, Vegetable, Gem, Fish, Egg, Milk, Cooking, Crafting, Mineral, Meat, Metal, Junk, Syrup, MonsterLoot, ArtisanGoods, and Seeds.
  "Edibility": 75, //Edibility is for health, energy is calculated by the game. For inedibile items, set to -300.
  "EdibleIsDrink": true,
  "EdibleIsDrink": true,
  "EdibleBuffs": {
    "Farming": 0,
    "Fishing": 0,
    "Mining": 0,
    "Luck": 2,
    "Foraging": 0,
    "MaxStamina": 25,
    "MagnetRadius": 0,
    "Speed": 3,
    "Defense": 2,
    "Attack": 0,
    "Duration": 700
  },
  "Price": 1250, //How much your item sells for.
  "IsColored": false, //(optional) Set this value to true if your product is colored. Primarily applies to flowers.
  "Recipe": {
    "ResultCount": 1,
    "Ingredients": [
      {
        //"Object": "Woman's Milk", //Breast Milk Category
        "Object": "-34", //Breast Milk Category
        "Count": 2
      },
      {
        //"Object": "Special Milk", //Cum Category
        "Object": "-35", //Cum Category
        "Count": 2
      }
    ],
    "IsDefault": true,
    "CanPurchase": true
  },
  "GiftTastes": //If an NPC isn't listed their gift taste will be neutral. If every NPC is specified you may remove unused categories.
  {
    "Love": [ "Abigail", " Caroline", " Haley" ], //Example of a single NPC
    "Like": [ "Robin", " Jodi", " Emily" ],
    "Neutral": null, //Example of `null`. Can also remove if not being used.
    "Dislike": [ "Sam", " Sebastien" ], //Example of multiple NPC
    "Hate": [ "Lewis", " George" ]
  },
  "ContextTags": [
    "cooking_item",
    "MTV_item"
  ],

  // Localization

  "NameLocalization": {
    "es": "Súper jugo", //Spanish
    "ko": "슈퍼 주스", //Korean
    "de": "Supersaft", //German
    "fr": "Super jus", //French
    "hu": "Szuperlé", //Hungarian
    "it": "Super succo", //Italian
    "ja": "スーパージュース", //Japanese
    "pt": "Super suco", //Portuguese
    "ru": "Супер сок", //Russian
    "tr": "Süper meyve suyu", //Turkish
    "zh": "超级果汁" //Chinese (Simplified)
  },
  "DescriptionLocalization": {
    "es": "La fusión perfecta de jugos masculinos y femeninos", //Spanish
    "ko": "수컷과 암컷 주스의 완벽한 융합", //Korean
    "de": "Die perfekte Fusion männlicher und weiblicher Säfte", //German
    "fr": "La fusion parfaite des jus mâles et femelles", //French
    "hu": "A férfi és női gyümölcslevek tökéletes fúziója", //Hungarian
    "it": "La fusione perfetta dei succhi maschi e femmine", //Italian
    "ja": "オスとメスのジュースの完璧な融合", //Japanese
    "pt": "A fusão perfeita de sucos masculinos e femininos", //Portuguese
    "ru": "Идеальное слияние мужских и женских соков", //Russian
    "tr": "Erkek ve kadın meyve sularının mükemmel füzyonu", //Turkish
    "zh": "雄性果汁的完美融合" //Chinese (Simplified)
  }
}